counter/hdl/counter.sv
module counter(
    input logic clk,
    input logic reset,
    input logic enable,
    output logic[3:0] count
);

initial begin 
    $dumpfile("counter_waves.vcd");
    $dumpvars;
end 

always_ff @(posedge clk or posedge reset) begin 
    if(reset) begin 
        count <= 0;
    end else begin 
        if(enable) begin 
            count <= count + 1;
        end 
    end 
end 
endmodule

counter/counter_waves.vcd
$date
	Mon Nov 17 15:55:57 2025
$end
$version
	Icarus Verilog
$end
$timescale
	1ps
$end
$scope module counter $end
$var wire 1 ! clk $end
$var wire 1 " enable $end
$var wire 1 # reset $end
$var reg 4 $ count [3:0] $end
$upscope $end
$enddefinitions $end
$comment Show the parameter values. $end
$dumpall
$end
#0
$dumpvars
b0 $
1#
z"
1!
$end
#5000
0!
#10000
1!
#15000
0!
#20000
0"
1!
0#
#25000
0!
#30000
1!
#35000
0!
#40000
1!
#45000
0!
#50000
1!
#55000
0!
#60000
1!
#65000
0!
#70000
1!
#75000
0!
#80000
1"
1!
#85000
0!
#90000
b1 $
1!
#95000
0!
#100000
b10 $
1!
#105000
0!
#110000
b11 $
1!
#115000
0!
#120000
b100 $
1!
#125000
0!
#130000
b101 $
1!
#135000
0!
#140000
b110 $
1!
#145000
0!
#150000
b111 $
1!
#155000
0!
#160000
b1000 $
1!
#165000
0!
#170000
b1001 $
1!
#175000
0!
#180000
b1010 $
1!
#185000
0!
#190000
b1011 $
1!
